[
  {
    "id":0,
    "name":"Daysi Pavao",
    "status":1
  },
  {
    "id":1,
    "name":"Margarita Mcdougald",
    "status":2
  },
  {
    "id":2,
    "name":"Sherry Brymer",
    "status":0
  },
  {
    "id":3,
    "name":"Margareta Crick",
    "status":2
  },
  {
    "id":4,
    "name":"Deanna Wickens",
    "status":1
  },
  {
    "id":5,
    "name":"Bambi Castonguay",
    "status":1
  },
  {
    "id":6,
    "name":"Rosamond Belvin",
    "status":2
  },
  {
    "id":7,
    "name":"Dyan Mcconnaughy",
    "status":1
  },
  {
    "id":8,
    "name":"Piedad Towner",
    "status":2
  },
  {
    "id":9,
    "name":"Tomika Angel",
    "status":0
  },
  {
    "id":10,
    "name":"Mayme Choe",
    "status":0
  },
  {
    "id":11,
    "name":"Alica Giorgio",
    "status":2
  },
  {
    "id":12,
    "name":"Heriberto Haberman",
    "status":1
  },
  {
    "id":13,
    "name":"Mari Kuehne",
    "status":1
  },
  {
    "id":14,
    "name":"Jesenia Swartz",
    "status":2
  },
  {
    "id":15,
    "name":"Arden Rohlfing",
    "status":1
  },
  {
    "id":16,
    "name":"Elly Straka",
    "status":1
  },
  {
    "id":17,
    "name":"Eldridge Chamblee",
    "status":1
  },
  {
    "id":18,
    "name":"Heike Cruzan",
    "status":0
  },
  {
    "id":19,
    "name":"Marita Damron",
    "status":1
  }
]